{
    "get": "fixtures",
    "parameters": {
        "id": "1209067"
    },
    "errors": [],
    "results": 1,
    "paging": {
        "current": 1,
        "total": 1
    },
    "response": [
        {
            "fixture": {
                "id": 1209067,
                "referee": null,
                "timezone": "UTC",
                "date": "2024-07-16T18:45:00+00:00",
                "timestamp": 1721155500,
                "periods": {
                    "first": 1721155500,
                    "second": 1721159100
                },
                "venue": {
                    "id": 20432,
                    "name": "The Artic Stadium",
                    "city": "London"
                },
                "status": {
                    "long": "Match Finished",
                    "short": "FT",
                    "elapsed": 90
                }
            },
            "league": {
                "id": 667,
                "name": "Friendlies Clubs",
                "country": "World",
                "logo": "https://media.api-sports.io/football/leagues/667.png",
                "flag": null,
                "season": 2024,
                "round": "Club Friendlies 3"
            },
            "teams": {
                "home": {
                    "id": 7636,
                    "name": "Cray Valley PM",
                    "logo": "https://media.api-sports.io/football/teams/7636.png",
                    "winner": false
                },
                "away": {
                    "id": 1840,
                    "name": "Ebbsfleet United",
                    "logo": "https://media.api-sports.io/football/teams/1840.png",
                    "winner": true
                }
            },
            "goals": {
                "home": 1,
                "away": 5
            },
            "score": {
                "halftime": {
                    "home": 0,
                    "away": 1
                },
                "fulltime": {
                    "home": 1,
                    "away": 5
                },
                "extratime": {
                    "home": null,
                    "away": null
                },
                "penalty": {
                    "home": null,
                    "away": null
                }
            },
            "events": [
                {
                    "time": {
                        "elapsed": 8,
                        "extra": null
                    },
                    "team": {
                        "id": 1840,
                        "name": "Ebbsfleet United",
                        "logo": "https://media.api-sports.io/football/teams/1840.png"
                    },
                    "player": {
                        "id": 44936,
                        "name": "C. Tanner"
                    },
                    "assist": {
                        "id": null,
                        "name": null
                    },
                    "type": "Goal",
                    "detail": "Normal Goal",
                    "comments": null
                },
                {
                    "time": {
                        "elapsed": 47,
                        "extra": null
                    },
                    "team": {
                        "id": 1840,
                        "name": "Ebbsfleet United",
                        "logo": "https://media.api-sports.io/football/teams/1840.png"
                    },
                    "player": {
                        "id": null,
                        "name": "Trialist D"
                    },
                    "assist": {
                        "id": null,
                        "name": null
                    },
                    "type": "Goal",
                    "detail": "Normal Goal",
                    "comments": null
                },
                {
                    "time": {
                        "elapsed": 68,
                        "extra": null
                    },
                    "team": {
                        "id": 1840,
                        "name": "Ebbsfleet United",
                        "logo": "https://media.api-sports.io/football/teams/1840.png"
                    },
                    "player": {
                        "id": 19490,
                        "name": "D. Samuel"
                    },
                    "assist": {
                        "id": null,
                        "name": null
                    },
                    "type": "Goal",
                    "detail": "Normal Goal",
                    "comments": null
                },
                {
                    "time": {
                        "elapsed": 75,
                        "extra": null
                    },
                    "team": {
                        "id": 7636,
                        "name": "Cray Valley PM",
                        "logo": "https://media.api-sports.io/football/teams/7636.png"
                    },
                    "player": {
                        "id": 156871,
                        "name": "J. Anau"
                    },
                    "assist": {
                        "id": null,
                        "name": null
                    },
                    "type": "Goal",
                    "detail": "Normal Goal",
                    "comments": null
                },
                {
                    "time": {
                        "elapsed": 80,
                        "extra": null
                    },
                    "team": {
                        "id": 1840,
                        "name": "Ebbsfleet United",
                        "logo": "https://media.api-sports.io/football/teams/1840.png"
                    },
                    "player": {
                        "id": 17905,
                        "name": "D. Poleon"
                    },
                    "assist": {
                        "id": null,
                        "name": null
                    },
                    "type": "Goal",
                    "detail": "Normal Goal",
                    "comments": null
                },
                {
                    "time": {
                        "elapsed": 88,
                        "extra": null
                    },
                    "team": {
                        "id": 1840,
                        "name": "Ebbsfleet United",
                        "logo": "https://media.api-sports.io/football/teams/1840.png"
                    },
                    "player": {
                        "id": 19490,
                        "name": "D. Samuel"
                    },
                    "assist": {
                        "id": null,
                        "name": null
                    },
                    "type": "Goal",
                    "detail": "Normal Goal",
                    "comments": null
                }
            ],
            "lineups": [],
            "statistics": [],
            "players": []
        }
    ]
}