{
    "get": "fixtures",
    "parameters": {
        "id": "1212086"
    },
    "errors": [],
    "results": 1,
    "paging": {
        "current": 1,
        "total": 1
    },
    "response": [
        {
            "fixture": {
                "id": 1212086,
                "referee": null,
                "timezone": "UTC",
                "date": "2024-08-09T16:00:00+00:00",
                "timestamp": 1723219200,
                "periods": {
                    "first": 1723219200,
                    "second": 1723222800
                },
                "venue": {
                    "id": 2492,
                    "name": "Stadion Letn\u00e1",
                    "city": "Zl\u00edn"
                },
                "status": {
                    "long": "Match Finished",
                    "short": "FT",
                    "elapsed": 90
                }
            },
            "league": {
                "id": 346,
                "name": "FNL",
                "country": "Czech-Republic",
                "logo": "https://media.api-sports.io/football/leagues/346.png",
                "flag": "https://media.api-sports.io/flags/cz.svg",
                "season": 2024,
                "round": "Regular Season - 5"
            },
            "teams": {
                "home": {
                    "id": 603,
                    "name": "Zlin",
                    "logo": "https://media.api-sports.io/football/teams/603.png",
                    "winner": true
                },
                "away": {
                    "id": 3729,
                    "name": "Viktoria \u017di\u017ekov",
                    "logo": "https://media.api-sports.io/football/teams/3729.png",
                    "winner": false
                }
            },
            "goals": {
                "home": 1,
                "away": 0
            },
            "score": {
                "halftime": {
                    "home": 1,
                    "away": 0
                },
                "fulltime": {
                    "home": 1,
                    "away": 0
                },
                "extratime": {
                    "home": null,
                    "away": null
                },
                "penalty": {
                    "home": null,
                    "away": null
                }
            },
            "events": [
                {
                    "time": {
                        "elapsed": 7,
                        "extra": null
                    },
                    "team": {
                        "id": 603,
                        "name": "Zlin",
                        "logo": "https://media.api-sports.io/football/teams/603.png"
                    },
                    "player": {
                        "id": 66313,
                        "name": "T. Poznar"
                    },
                    "assist": {
                        "id": null,
                        "name": null
                    },
                    "type": "Goal",
                    "detail": "Normal Goal",
                    "comments": null
                },
                {
                    "time": {
                        "elapsed": 40,
                        "extra": null
                    },
                    "team": {
                        "id": 3729,
                        "name": "Viktoria \u017di\u017ekov",
                        "logo": "https://media.api-sports.io/football/teams/3729.png"
                    },
                    "player": {
                        "id": 119904,
                        "name": "D. Broukal"
                    },
                    "assist": {
                        "id": null,
                        "name": null
                    },
                    "type": "Card",
                    "detail": "Yellow Card",
                    "comments": null
                },
                {
                    "time": {
                        "elapsed": 42,
                        "extra": null
                    },
                    "team": {
                        "id": 603,
                        "name": "Zlin",
                        "logo": "https://media.api-sports.io/football/teams/603.png"
                    },
                    "player": {
                        "id": 314227,
                        "name": "D. Tkac"
                    },
                    "assist": {
                        "id": null,
                        "name": null
                    },
                    "type": "Card",
                    "detail": "Yellow Card",
                    "comments": null
                },
                {
                    "time": {
                        "elapsed": 46,
                        "extra": null
                    },
                    "team": {
                        "id": 603,
                        "name": "Zlin",
                        "logo": "https://media.api-sports.io/football/teams/603.png"
                    },
                    "player": {
                        "id": 91597,
                        "name": "J. Didiba"
                    },
                    "assist": {
                        "id": 66680,
                        "name": "D. Machalik"
                    },
                    "type": "subst",
                    "detail": "Substitution 1",
                    "comments": null
                },
                {
                    "time": {
                        "elapsed": 61,
                        "extra": null
                    },
                    "team": {
                        "id": 603,
                        "name": "Zlin",
                        "logo": "https://media.api-sports.io/football/teams/603.png"
                    },
                    "player": {
                        "id": 119906,
                        "name": "J. Cernin"
                    },
                    "assist": {
                        "id": null,
                        "name": null
                    },
                    "type": "Card",
                    "detail": "Yellow Card",
                    "comments": null
                },
                {
                    "time": {
                        "elapsed": 63,
                        "extra": null
                    },
                    "team": {
                        "id": 3729,
                        "name": "Viktoria \u017di\u017ekov",
                        "logo": "https://media.api-sports.io/football/teams/3729.png"
                    },
                    "player": {
                        "id": 66696,
                        "name": "D. Klusak"
                    },
                    "assist": {
                        "id": null,
                        "name": null
                    },
                    "type": "Card",
                    "detail": "Yellow Card",
                    "comments": null
                },
                {
                    "time": {
                        "elapsed": 67,
                        "extra": null
                    },
                    "team": {
                        "id": 3729,
                        "name": "Viktoria \u017di\u017ekov",
                        "logo": "https://media.api-sports.io/football/teams/3729.png"
                    },
                    "player": {
                        "id": 66460,
                        "name": "V. Prosek"
                    },
                    "assist": {
                        "id": 66696,
                        "name": "D. Klusak"
                    },
                    "type": "subst",
                    "detail": "Substitution 1",
                    "comments": null
                },
                {
                    "time": {
                        "elapsed": 76,
                        "extra": null
                    },
                    "team": {
                        "id": 603,
                        "name": "Zlin",
                        "logo": "https://media.api-sports.io/football/teams/603.png"
                    },
                    "player": {
                        "id": 66355,
                        "name": "P. Brandner"
                    },
                    "assist": {
                        "id": null,
                        "name": "Z. Natchkebia"
                    },
                    "type": "subst",
                    "detail": "Substitution 2",
                    "comments": null
                },
                {
                    "time": {
                        "elapsed": 76,
                        "extra": null
                    },
                    "team": {
                        "id": 603,
                        "name": "Zlin",
                        "logo": "https://media.api-sports.io/football/teams/603.png"
                    },
                    "player": {
                        "id": 66149,
                        "name": "R. Reiter"
                    },
                    "assist": {
                        "id": 62066,
                        "name": "V. Vukadinovic"
                    },
                    "type": "subst",
                    "detail": "Substitution 3",
                    "comments": null
                },
                {
                    "time": {
                        "elapsed": 77,
                        "extra": null
                    },
                    "team": {
                        "id": 3729,
                        "name": "Viktoria \u017di\u017ekov",
                        "logo": "https://media.api-sports.io/football/teams/3729.png"
                    },
                    "player": {
                        "id": 176442,
                        "name": "J. Sodoma"
                    },
                    "assist": {
                        "id": 66086,
                        "name": "J. Divisek"
                    },
                    "type": "subst",
                    "detail": "Substitution 2",
                    "comments": null
                },
                {
                    "time": {
                        "elapsed": 77,
                        "extra": null
                    },
                    "team": {
                        "id": 3729,
                        "name": "Viktoria \u017di\u017ekov",
                        "logo": "https://media.api-sports.io/football/teams/3729.png"
                    },
                    "player": {
                        "id": 180966,
                        "name": "D. Gembicky"
                    },
                    "assist": {
                        "id": 134744,
                        "name": "M. Honig"
                    },
                    "type": "subst",
                    "detail": "Substitution 3",
                    "comments": null
                },
                {
                    "time": {
                        "elapsed": 84,
                        "extra": null
                    },
                    "team": {
                        "id": 3729,
                        "name": "Viktoria \u017di\u017ekov",
                        "logo": "https://media.api-sports.io/football/teams/3729.png"
                    },
                    "player": {
                        "id": 66075,
                        "name": "M. Jirasek"
                    },
                    "assist": {
                        "id": 147824,
                        "name": "A. Petrak"
                    },
                    "type": "subst",
                    "detail": "Substitution 4",
                    "comments": null
                },
                {
                    "time": {
                        "elapsed": 84,
                        "extra": null
                    },
                    "team": {
                        "id": 3729,
                        "name": "Viktoria \u017di\u017ekov",
                        "logo": "https://media.api-sports.io/football/teams/3729.png"
                    },
                    "player": {
                        "id": 66657,
                        "name": "D. Sixta"
                    },
                    "assist": {
                        "id": 66735,
                        "name": "A. Batioja"
                    },
                    "type": "subst",
                    "detail": "Substitution 5",
                    "comments": null
                },
                {
                    "time": {
                        "elapsed": 87,
                        "extra": null
                    },
                    "team": {
                        "id": 3729,
                        "name": "Viktoria \u017di\u017ekov",
                        "logo": "https://media.api-sports.io/football/teams/3729.png"
                    },
                    "player": {
                        "id": 180966,
                        "name": "D. Gembicky"
                    },
                    "assist": {
                        "id": null,
                        "name": null
                    },
                    "type": "Card",
                    "detail": "Yellow Card",
                    "comments": null
                },
                {
                    "time": {
                        "elapsed": 88,
                        "extra": null
                    },
                    "team": {
                        "id": 603,
                        "name": "Zlin",
                        "logo": "https://media.api-sports.io/football/teams/603.png"
                    },
                    "player": {
                        "id": 337830,
                        "name": "P. Kulisek"
                    },
                    "assist": {
                        "id": 281983,
                        "name": "C. Nombil"
                    },
                    "type": "subst",
                    "detail": "Substitution 4",
                    "comments": null
                },
                {
                    "time": {
                        "elapsed": 90,
                        "extra": 3
                    },
                    "team": {
                        "id": 603,
                        "name": "Zlin",
                        "logo": "https://media.api-sports.io/football/teams/603.png"
                    },
                    "player": {
                        "id": null,
                        "name": "M. Slouk"
                    },
                    "assist": {
                        "id": 314227,
                        "name": "D. Tkac"
                    },
                    "type": "subst",
                    "detail": "Substitution 5",
                    "comments": null
                }
            ],
            "lineups": [],
            "statistics": [],
            "players": []
        }
    ]
}