{
    "get": "fixtures",
    "parameters": {
        "id": "1253504"
    },
    "errors": [],
    "results": 1,
    "paging": {
        "current": 1,
        "total": 1
    },
    "response": [
        {
            "fixture": {
                "id": 1253504,
                "referee": "J. Quinteros",
                "timezone": "UTC",
                "date": "2024-08-03T21:30:00+00:00",
                "timestamp": 1722720600,
                "periods": {
                    "first": 1722720600,
                    "second": 1722724200
                },
                "venue": {
                    "id": 3287,
                    "name": "Estadio Sergio Torres Rivera",
                    "city": "Usulut\u00e1n"
                },
                "status": {
                    "long": "Match Finished",
                    "short": "FT",
                    "elapsed": 90
                }
            },
            "league": {
                "id": 370,
                "name": "Primera Division",
                "country": "El-Salvador",
                "logo": "https://media.api-sports.io/football/leagues/370.png",
                "flag": "https://media.api-sports.io/flags/sv.svg",
                "season": 2024,
                "round": "Apertura - 3"
            },
            "teams": {
                "home": {
                    "id": 4303,
                    "name": "Firpo",
                    "logo": "https://media.api-sports.io/football/teams/4303.png",
                    "winner": false
                },
                "away": {
                    "id": 24530,
                    "name": "Cacahuatique",
                    "logo": "https://media.api-sports.io/football/teams/24530.png",
                    "winner": true
                }
            },
            "goals": {
                "home": 1,
                "away": 3
            },
            "score": {
                "halftime": {
                    "home": 1,
                    "away": 3
                },
                "fulltime": {
                    "home": 1,
                    "away": 3
                },
                "extratime": {
                    "home": null,
                    "away": null
                },
                "penalty": {
                    "home": null,
                    "away": null
                }
            },
            "events": [
                {
                    "time": {
                        "elapsed": 13,
                        "extra": null
                    },
                    "team": {
                        "id": 4303,
                        "name": "Firpo",
                        "logo": "https://media.api-sports.io/football/teams/4303.png"
                    },
                    "player": {
                        "id": 309903,
                        "name": "M. Cerritos"
                    },
                    "assist": {
                        "id": null,
                        "name": null
                    },
                    "type": "Goal",
                    "detail": "Normal Goal",
                    "comments": null
                },
                {
                    "time": {
                        "elapsed": 17,
                        "extra": null
                    },
                    "team": {
                        "id": 24530,
                        "name": "Cacahuatique",
                        "logo": "https://media.api-sports.io/football/teams/24530.png"
                    },
                    "player": {
                        "id": 59710,
                        "name": "J. Grueso"
                    },
                    "assist": {
                        "id": null,
                        "name": null
                    },
                    "type": "Goal",
                    "detail": "Normal Goal",
                    "comments": null
                },
                {
                    "time": {
                        "elapsed": 28,
                        "extra": null
                    },
                    "team": {
                        "id": 24530,
                        "name": "Cacahuatique",
                        "logo": "https://media.api-sports.io/football/teams/24530.png"
                    },
                    "player": {
                        "id": 108950,
                        "name": "J. Turcios"
                    },
                    "assist": {
                        "id": null,
                        "name": null
                    },
                    "type": "Goal",
                    "detail": "Normal Goal",
                    "comments": null
                },
                {
                    "time": {
                        "elapsed": 43,
                        "extra": null
                    },
                    "team": {
                        "id": 24530,
                        "name": "Cacahuatique",
                        "logo": "https://media.api-sports.io/football/teams/24530.png"
                    },
                    "player": {
                        "id": 59710,
                        "name": "J. Grueso"
                    },
                    "assist": {
                        "id": null,
                        "name": null
                    },
                    "type": "Goal",
                    "detail": "Penalty",
                    "comments": null
                },
                {
                    "time": {
                        "elapsed": 45,
                        "extra": null
                    },
                    "team": {
                        "id": 4303,
                        "name": "Firpo",
                        "logo": "https://media.api-sports.io/football/teams/4303.png"
                    },
                    "player": {
                        "id": 475313,
                        "name": "J. Montoya"
                    },
                    "assist": {
                        "id": 405653,
                        "name": "E. Gumero"
                    },
                    "type": "subst",
                    "detail": "Substitution 1",
                    "comments": null
                },
                {
                    "time": {
                        "elapsed": 46,
                        "extra": null
                    },
                    "team": {
                        "id": 4303,
                        "name": "Firpo",
                        "logo": "https://media.api-sports.io/football/teams/4303.png"
                    },
                    "player": {
                        "id": 108760,
                        "name": "B. Mart\u00ednez"
                    },
                    "assist": {
                        "id": 141311,
                        "name": "Guilherme Silva"
                    },
                    "type": "subst",
                    "detail": "Substitution 2",
                    "comments": null
                },
                {
                    "time": {
                        "elapsed": 46,
                        "extra": null
                    },
                    "team": {
                        "id": 4303,
                        "name": "Firpo",
                        "logo": "https://media.api-sports.io/football/teams/4303.png"
                    },
                    "player": {
                        "id": 477557,
                        "name": "K. Mej\u00eda"
                    },
                    "assist": {
                        "id": 108738,
                        "name": "V. Garc\u00eda"
                    },
                    "type": "subst",
                    "detail": "Substitution 3",
                    "comments": null
                },
                {
                    "time": {
                        "elapsed": 52,
                        "extra": null
                    },
                    "team": {
                        "id": 4303,
                        "name": "Firpo",
                        "logo": "https://media.api-sports.io/football/teams/4303.png"
                    },
                    "player": {
                        "id": 325081,
                        "name": "R. Melgar"
                    },
                    "assist": {
                        "id": 346253,
                        "name": "D. Flores"
                    },
                    "type": "subst",
                    "detail": "Substitution 4",
                    "comments": null
                },
                {
                    "time": {
                        "elapsed": 65,
                        "extra": null
                    },
                    "team": {
                        "id": 24530,
                        "name": "Cacahuatique",
                        "logo": "https://media.api-sports.io/football/teams/24530.png"
                    },
                    "player": {
                        "id": 478327,
                        "name": "J. Ramos"
                    },
                    "assist": {
                        "id": 108824,
                        "name": "A. M\u00e1rquez"
                    },
                    "type": "subst",
                    "detail": "Substitution 1",
                    "comments": null
                },
                {
                    "time": {
                        "elapsed": 65,
                        "extra": null
                    },
                    "team": {
                        "id": 24530,
                        "name": "Cacahuatique",
                        "logo": "https://media.api-sports.io/football/teams/24530.png"
                    },
                    "player": {
                        "id": 326005,
                        "name": "K. Hern\u00e1ndez"
                    },
                    "assist": {
                        "id": 108654,
                        "name": "C. Galeas"
                    },
                    "type": "subst",
                    "detail": "Substitution 2",
                    "comments": null
                },
                {
                    "time": {
                        "elapsed": 84,
                        "extra": null
                    },
                    "team": {
                        "id": 24530,
                        "name": "Cacahuatique",
                        "logo": "https://media.api-sports.io/football/teams/24530.png"
                    },
                    "player": {
                        "id": 108950,
                        "name": "J. Turcios"
                    },
                    "assist": {
                        "id": 478905,
                        "name": "K. Ventura"
                    },
                    "type": "subst",
                    "detail": "Substitution 3",
                    "comments": null
                }
            ],
            "lineups": [
                {
                    "team": {
                        "id": 4303,
                        "name": "Firpo",
                        "logo": "https://media.api-sports.io/football/teams/4303.png",
                        "colors": null
                    },
                    "coach": {
                        "id": 21689,
                        "name": "G. \u00c1lvarez",
                        "photo": "https://media.api-sports.io/football/coachs/21689.png"
                    },
                    "formation": null,
                    "startXI": [
                        {
                            "player": {
                                "id": 108914,
                                "name": "W. Hern\u00e1ndez",
                                "number": null,
                                "pos": null,
                                "grid": null
                            }
                        },
                        {
                            "player": {
                                "id": 331822,
                                "name": "L. Claros",
                                "number": null,
                                "pos": null,
                                "grid": null
                            }
                        },
                        {
                            "player": {
                                "id": 108737,
                                "name": "S. Henr\u00edquez",
                                "number": null,
                                "pos": null,
                                "grid": null
                            }
                        },
                        {
                            "player": {
                                "id": 157786,
                                "name": "J. Quintanilla",
                                "number": null,
                                "pos": null,
                                "grid": null
                            }
                        },
                        {
                            "player": {
                                "id": 325081,
                                "name": "R. Melgar",
                                "number": null,
                                "pos": null,
                                "grid": null
                            }
                        },
                        {
                            "player": {
                                "id": 325290,
                                "name": "W. Arizala",
                                "number": null,
                                "pos": null,
                                "grid": null
                            }
                        },
                        {
                            "player": {
                                "id": 108760,
                                "name": "B. Mart\u00ednez",
                                "number": null,
                                "pos": null,
                                "grid": null
                            }
                        },
                        {
                            "player": {
                                "id": 309903,
                                "name": "M. Cerritos",
                                "number": null,
                                "pos": null,
                                "grid": null
                            }
                        },
                        {
                            "player": {
                                "id": 449327,
                                "name": "K. Ascencio",
                                "number": null,
                                "pos": null,
                                "grid": null
                            }
                        },
                        {
                            "player": {
                                "id": 475313,
                                "name": "J. Montoya",
                                "number": null,
                                "pos": null,
                                "grid": null
                            }
                        },
                        {
                            "player": {
                                "id": 477557,
                                "name": "K. Mej\u00eda",
                                "number": null,
                                "pos": null,
                                "grid": null
                            }
                        }
                    ],
                    "substitutes": [
                        {
                            "player": {
                                "id": 405653,
                                "name": "E. Gumero",
                                "number": null,
                                "pos": null,
                                "grid": null
                            }
                        },
                        {
                            "player": {
                                "id": 141311,
                                "name": "Guilherme Silva",
                                "number": null,
                                "pos": null,
                                "grid": null
                            }
                        },
                        {
                            "player": {
                                "id": 108738,
                                "name": "V. Garc\u00eda",
                                "number": null,
                                "pos": null,
                                "grid": null
                            }
                        },
                        {
                            "player": {
                                "id": 346253,
                                "name": "D. Flores",
                                "number": null,
                                "pos": null,
                                "grid": null
                            }
                        }
                    ]
                },
                {
                    "team": {
                        "id": 24530,
                        "name": "Cacahuatique",
                        "logo": "https://media.api-sports.io/football/teams/24530.png",
                        "colors": null
                    },
                    "coach": {
                        "id": 22782,
                        "name": "E. Corti",
                        "photo": "https://media.api-sports.io/football/coachs/22782.png"
                    },
                    "formation": null,
                    "startXI": [
                        {
                            "player": {
                                "id": 108951,
                                "name": "\u00d3. S\u00e1nchez",
                                "number": null,
                                "pos": null,
                                "grid": null
                            }
                        },
                        {
                            "player": {
                                "id": 108845,
                                "name": "C. Hern\u00e1ndez",
                                "number": null,
                                "pos": null,
                                "grid": null
                            }
                        },
                        {
                            "player": {
                                "id": 108787,
                                "name": "R. Aparicio",
                                "number": null,
                                "pos": null,
                                "grid": null
                            }
                        },
                        {
                            "player": {
                                "id": 432679,
                                "name": "F. Carballo",
                                "number": null,
                                "pos": null,
                                "grid": null
                            }
                        },
                        {
                            "player": {
                                "id": 108731,
                                "name": "R. G\u00f3mez",
                                "number": null,
                                "pos": null,
                                "grid": null
                            }
                        },
                        {
                            "player": {
                                "id": 108950,
                                "name": "J. Turcios",
                                "number": null,
                                "pos": null,
                                "grid": null
                            }
                        },
                        {
                            "player": {
                                "id": 59710,
                                "name": "J. Grueso",
                                "number": null,
                                "pos": null,
                                "grid": null
                            }
                        },
                        {
                            "player": {
                                "id": 326005,
                                "name": "K. Hern\u00e1ndez",
                                "number": null,
                                "pos": null,
                                "grid": null
                            }
                        },
                        {
                            "player": {
                                "id": 411408,
                                "name": "P. Ben\u00edtez",
                                "number": null,
                                "pos": null,
                                "grid": null
                            }
                        },
                        {
                            "player": {
                                "id": 475741,
                                "name": "B. Amaya",
                                "number": null,
                                "pos": null,
                                "grid": null
                            }
                        },
                        {
                            "player": {
                                "id": 478327,
                                "name": "J. Ramos",
                                "number": null,
                                "pos": null,
                                "grid": null
                            }
                        }
                    ],
                    "substitutes": [
                        {
                            "player": {
                                "id": 108824,
                                "name": "A. M\u00e1rquez",
                                "number": null,
                                "pos": null,
                                "grid": null
                            }
                        },
                        {
                            "player": {
                                "id": 108654,
                                "name": "C. Galeas",
                                "number": null,
                                "pos": null,
                                "grid": null
                            }
                        },
                        {
                            "player": {
                                "id": 478905,
                                "name": "K. Ventura",
                                "number": null,
                                "pos": null,
                                "grid": null
                            }
                        }
                    ]
                }
            ],
            "statistics": [],
            "players": []
        }
    ]
}