{
    "get": "fixtures",
    "parameters": {
        "id": "1253244"
    },
    "errors": [],
    "results": 1,
    "paging": {
        "current": 1,
        "total": 1
    },
    "response": [
        {
            "fixture": {
                "id": 1253244,
                "referee": "Murilo Ugolini Klein",
                "timezone": "UTC",
                "date": "2024-07-27T21:30:00+00:00",
                "timestamp": 1722115800,
                "periods": {
                    "first": 1722115800,
                    "second": 1722119400
                },
                "venue": {
                    "id": 215,
                    "name": "Est\u00e1dio dos Eucaliptos",
                    "city": "Santa Cruz do Sul, Rio Grande do Sul"
                },
                "status": {
                    "long": "Match Finished",
                    "short": "FT",
                    "elapsed": 90
                }
            },
            "league": {
                "id": 76,
                "name": "Serie D",
                "country": "Brazil",
                "logo": "https://media.api-sports.io/football/leagues/76.png",
                "flag": "https://media.api-sports.io/flags/br.svg",
                "season": 2024,
                "round": "Round of 32"
            },
            "teams": {
                "home": {
                    "id": 2205,
                    "name": "Avenida",
                    "logo": "https://media.api-sports.io/football/teams/2205.png",
                    "winner": null
                },
                "away": {
                    "id": 1201,
                    "name": "Inter De Limeira",
                    "logo": "https://media.api-sports.io/football/teams/1201.png",
                    "winner": null
                }
            },
            "goals": {
                "home": 0,
                "away": 0
            },
            "score": {
                "halftime": {
                    "home": 0,
                    "away": 0
                },
                "fulltime": {
                    "home": 0,
                    "away": 0
                },
                "extratime": {
                    "home": null,
                    "away": null
                },
                "penalty": {
                    "home": null,
                    "away": null
                }
            },
            "events": [
                {
                    "time": {
                        "elapsed": 39,
                        "extra": null
                    },
                    "team": {
                        "id": 2205,
                        "name": "Avenida",
                        "logo": "https://media.api-sports.io/football/teams/2205.png"
                    },
                    "player": {
                        "id": 80661,
                        "name": "Carlos Alberto"
                    },
                    "assist": {
                        "id": 308499,
                        "name": "Laion"
                    },
                    "type": "subst",
                    "detail": "Substitution 1",
                    "comments": null
                },
                {
                    "time": {
                        "elapsed": 39,
                        "extra": null
                    },
                    "team": {
                        "id": 1201,
                        "name": "Inter De Limeira",
                        "logo": "https://media.api-sports.io/football/teams/1201.png"
                    },
                    "player": {
                        "id": 9309,
                        "name": "Lucas Rocha"
                    },
                    "assist": {
                        "id": 197428,
                        "name": "Williams Bahia"
                    },
                    "type": "subst",
                    "detail": "Substitution 1",
                    "comments": null
                },
                {
                    "time": {
                        "elapsed": 46,
                        "extra": null
                    },
                    "team": {
                        "id": 1201,
                        "name": "Inter De Limeira",
                        "logo": "https://media.api-sports.io/football/teams/1201.png"
                    },
                    "player": {
                        "id": 474235,
                        "name": "Leonardo"
                    },
                    "assist": {
                        "id": 9223,
                        "name": "Erick Luis"
                    },
                    "type": "subst",
                    "detail": "Substitution 2",
                    "comments": null
                },
                {
                    "time": {
                        "elapsed": 46,
                        "extra": null
                    },
                    "team": {
                        "id": 1201,
                        "name": "Inter De Limeira",
                        "logo": "https://media.api-sports.io/football/teams/1201.png"
                    },
                    "player": {
                        "id": 292336,
                        "name": "Lucas Brune"
                    },
                    "assist": {
                        "id": 306364,
                        "name": "Juninho"
                    },
                    "type": "subst",
                    "detail": "Substitution 3",
                    "comments": null
                },
                {
                    "time": {
                        "elapsed": 66,
                        "extra": null
                    },
                    "team": {
                        "id": 2205,
                        "name": "Avenida",
                        "logo": "https://media.api-sports.io/football/teams/2205.png"
                    },
                    "player": {
                        "id": 114528,
                        "name": "Maikon Aquino"
                    },
                    "assist": {
                        "id": 9824,
                        "name": "Branquinho"
                    },
                    "type": "subst",
                    "detail": "Substitution 2",
                    "comments": null
                },
                {
                    "time": {
                        "elapsed": 66,
                        "extra": null
                    },
                    "team": {
                        "id": 2205,
                        "name": "Avenida",
                        "logo": "https://media.api-sports.io/football/teams/2205.png"
                    },
                    "player": {
                        "id": 54823,
                        "name": "Fl\u00e1vio Torres"
                    },
                    "assist": {
                        "id": 9857,
                        "name": "Wesley Pacheco"
                    },
                    "type": "subst",
                    "detail": "Substitution 3",
                    "comments": null
                },
                {
                    "time": {
                        "elapsed": 76,
                        "extra": null
                    },
                    "team": {
                        "id": 1201,
                        "name": "Inter De Limeira",
                        "logo": "https://media.api-sports.io/football/teams/1201.png"
                    },
                    "player": {
                        "id": 237737,
                        "name": "Cesinha"
                    },
                    "assist": {
                        "id": 10064,
                        "name": "Rhuan Silveira"
                    },
                    "type": "subst",
                    "detail": "Substitution 4",
                    "comments": null
                },
                {
                    "time": {
                        "elapsed": 76,
                        "extra": null
                    },
                    "team": {
                        "id": 1201,
                        "name": "Inter De Limeira",
                        "logo": "https://media.api-sports.io/football/teams/1201.png"
                    },
                    "player": {
                        "id": 55295,
                        "name": "Albano"
                    },
                    "assist": {
                        "id": 333006,
                        "name": "Vin\u00edcius Amaral"
                    },
                    "type": "subst",
                    "detail": "Substitution 5",
                    "comments": null
                },
                {
                    "time": {
                        "elapsed": 78,
                        "extra": null
                    },
                    "team": {
                        "id": 2205,
                        "name": "Avenida",
                        "logo": "https://media.api-sports.io/football/teams/2205.png"
                    },
                    "player": {
                        "id": 53948,
                        "name": "Bruno Camilo"
                    },
                    "assist": {
                        "id": 106441,
                        "name": "Gabriel Tonini"
                    },
                    "type": "subst",
                    "detail": "Substitution 4",
                    "comments": null
                },
                {
                    "time": {
                        "elapsed": 78,
                        "extra": null
                    },
                    "team": {
                        "id": 2205,
                        "name": "Avenida",
                        "logo": "https://media.api-sports.io/football/teams/2205.png"
                    },
                    "player": {
                        "id": 109665,
                        "name": "Tony Junior"
                    },
                    "assist": {
                        "id": 64042,
                        "name": "Mauri"
                    },
                    "type": "subst",
                    "detail": "Substitution 5",
                    "comments": null
                }
            ],
            "lineups": [
                {
                    "team": {
                        "id": 2205,
                        "name": "Avenida",
                        "logo": "https://media.api-sports.io/football/teams/2205.png",
                        "colors": null
                    },
                    "coach": {
                        "id": 14215,
                        "name": "Wiliam Campos",
                        "photo": "https://media.api-sports.io/football/coachs/14215.png"
                    },
                    "formation": null,
                    "startXI": [
                        {
                            "player": {
                                "id": 157459,
                                "name": "Rafael Pin",
                                "number": null,
                                "pos": null,
                                "grid": null
                            }
                        },
                        {
                            "player": {
                                "id": 54007,
                                "name": "Micael",
                                "number": null,
                                "pos": null,
                                "grid": null
                            }
                        },
                        {
                            "player": {
                                "id": 10449,
                                "name": "Celsinho",
                                "number": null,
                                "pos": null,
                                "grid": null
                            }
                        },
                        {
                            "player": {
                                "id": 67203,
                                "name": "Diego Ivo",
                                "number": null,
                                "pos": null,
                                "grid": null
                            }
                        },
                        {
                            "player": {
                                "id": 80488,
                                "name": "C\u00e9sar Nunes",
                                "number": null,
                                "pos": null,
                                "grid": null
                            }
                        },
                        {
                            "player": {
                                "id": 80652,
                                "name": "Amaral",
                                "number": null,
                                "pos": null,
                                "grid": null
                            }
                        },
                        {
                            "player": {
                                "id": 80661,
                                "name": "Carlos Alberto",
                                "number": null,
                                "pos": null,
                                "grid": null
                            }
                        },
                        {
                            "player": {
                                "id": 53948,
                                "name": "Bruno Camilo",
                                "number": null,
                                "pos": null,
                                "grid": null
                            }
                        },
                        {
                            "player": {
                                "id": 54823,
                                "name": "Fl\u00e1vio Torres",
                                "number": null,
                                "pos": null,
                                "grid": null
                            }
                        },
                        {
                            "player": {
                                "id": 114528,
                                "name": "Maikon Aquino",
                                "number": null,
                                "pos": null,
                                "grid": null
                            }
                        },
                        {
                            "player": {
                                "id": 109665,
                                "name": "Tony Junior",
                                "number": null,
                                "pos": null,
                                "grid": null
                            }
                        }
                    ],
                    "substitutes": [
                        {
                            "player": {
                                "id": 308499,
                                "name": "Laion",
                                "number": null,
                                "pos": null,
                                "grid": null
                            }
                        },
                        {
                            "player": {
                                "id": 9824,
                                "name": "Branquinho",
                                "number": null,
                                "pos": null,
                                "grid": null
                            }
                        },
                        {
                            "player": {
                                "id": 9857,
                                "name": "Wesley Pacheco",
                                "number": null,
                                "pos": null,
                                "grid": null
                            }
                        },
                        {
                            "player": {
                                "id": 106441,
                                "name": "Gabriel Tonini",
                                "number": null,
                                "pos": null,
                                "grid": null
                            }
                        },
                        {
                            "player": {
                                "id": 64042,
                                "name": "Mauri",
                                "number": null,
                                "pos": null,
                                "grid": null
                            }
                        },
                        {
                            "player": {
                                "id": 428020,
                                "name": "Gabriel Toebe",
                                "number": null,
                                "pos": null,
                                "grid": null
                            }
                        },
                        {
                            "player": {
                                "id": 9983,
                                "name": "Alan Cardoso",
                                "number": null,
                                "pos": null,
                                "grid": null
                            }
                        },
                        {
                            "player": {
                                "id": 54813,
                                "name": "Alexandre Camargo",
                                "number": null,
                                "pos": null,
                                "grid": null
                            }
                        },
                        {
                            "player": {
                                "id": 54752,
                                "name": "Bruno Jesus",
                                "number": null,
                                "pos": null,
                                "grid": null
                            }
                        },
                        {
                            "player": {
                                "id": 237615,
                                "name": "Jhonata Lima",
                                "number": null,
                                "pos": null,
                                "grid": null
                            }
                        },
                        {
                            "player": {
                                "id": 308503,
                                "name": "Kevlin",
                                "number": null,
                                "pos": null,
                                "grid": null
                            }
                        },
                        {
                            "player": {
                                "id": 281868,
                                "name": "Vitor Dadalt",
                                "number": null,
                                "pos": null,
                                "grid": null
                            }
                        }
                    ]
                },
                {
                    "team": {
                        "id": 1201,
                        "name": "Inter De Limeira",
                        "logo": "https://media.api-sports.io/football/teams/1201.png",
                        "colors": null
                    },
                    "coach": {
                        "id": 237,
                        "name": "Felipe Concei\u00e7\u00e3o",
                        "photo": "https://media.api-sports.io/football/coachs/237.png"
                    },
                    "formation": null,
                    "startXI": [
                        {
                            "player": {
                                "id": 9479,
                                "name": "Andr\u00e9 Luiz",
                                "number": null,
                                "pos": null,
                                "grid": null
                            }
                        },
                        {
                            "player": {
                                "id": 9836,
                                "name": "Diego Jussani",
                                "number": null,
                                "pos": null,
                                "grid": null
                            }
                        },
                        {
                            "player": {
                                "id": 9309,
                                "name": "Lucas Rocha",
                                "number": null,
                                "pos": null,
                                "grid": null
                            }
                        },
                        {
                            "player": {
                                "id": 195307,
                                "name": "Alysson Dutra",
                                "number": null,
                                "pos": null,
                                "grid": null
                            }
                        },
                        {
                            "player": {
                                "id": 197361,
                                "name": "Leocovick",
                                "number": null,
                                "pos": null,
                                "grid": null
                            }
                        },
                        {
                            "player": {
                                "id": 279014,
                                "name": "Eduardo Porto",
                                "number": null,
                                "pos": null,
                                "grid": null
                            }
                        },
                        {
                            "player": {
                                "id": 237737,
                                "name": "Cesinha",
                                "number": null,
                                "pos": null,
                                "grid": null
                            }
                        },
                        {
                            "player": {
                                "id": 55295,
                                "name": "Albano",
                                "number": null,
                                "pos": null,
                                "grid": null
                            }
                        },
                        {
                            "player": {
                                "id": 301213,
                                "name": "Marlon",
                                "number": null,
                                "pos": null,
                                "grid": null
                            }
                        },
                        {
                            "player": {
                                "id": 292336,
                                "name": "Lucas Brune",
                                "number": null,
                                "pos": null,
                                "grid": null
                            }
                        },
                        {
                            "player": {
                                "id": 474235,
                                "name": "Leonardo",
                                "number": null,
                                "pos": null,
                                "grid": null
                            }
                        }
                    ],
                    "substitutes": [
                        {
                            "player": {
                                "id": 197428,
                                "name": "Williams Bahia",
                                "number": null,
                                "pos": null,
                                "grid": null
                            }
                        },
                        {
                            "player": {
                                "id": 9223,
                                "name": "Erick Luis",
                                "number": null,
                                "pos": null,
                                "grid": null
                            }
                        },
                        {
                            "player": {
                                "id": 306364,
                                "name": "Juninho",
                                "number": null,
                                "pos": null,
                                "grid": null
                            }
                        },
                        {
                            "player": {
                                "id": 10064,
                                "name": "Rhuan Silveira",
                                "number": null,
                                "pos": null,
                                "grid": null
                            }
                        },
                        {
                            "player": {
                                "id": 333006,
                                "name": "Vin\u00edcius Amaral",
                                "number": null,
                                "pos": null,
                                "grid": null
                            }
                        },
                        {
                            "player": {
                                "id": 159902,
                                "name": "Vin\u00edcius Almeida",
                                "number": null,
                                "pos": null,
                                "grid": null
                            }
                        },
                        {
                            "player": {
                                "id": 265293,
                                "name": "Jo\u00e3o Felipe",
                                "number": null,
                                "pos": null,
                                "grid": null
                            }
                        },
                        {
                            "player": {
                                "id": 476788,
                                "name": "Jo\u00e3o Vitor",
                                "number": null,
                                "pos": null,
                                "grid": null
                            }
                        },
                        {
                            "player": {
                                "id": 64921,
                                "name": "Joel",
                                "number": null,
                                "pos": null,
                                "grid": null
                            }
                        },
                        {
                            "player": {
                                "id": 9428,
                                "name": "Kadu",
                                "number": null,
                                "pos": null,
                                "grid": null
                            }
                        },
                        {
                            "player": {
                                "id": 54066,
                                "name": "Kau\u00ea",
                                "number": null,
                                "pos": null,
                                "grid": null
                            }
                        },
                        {
                            "player": {
                                "id": 283030,
                                "name": "Ueslei Brito",
                                "number": null,
                                "pos": null,
                                "grid": null
                            }
                        }
                    ]
                }
            ],
            "statistics": [],
            "players": []
        }
    ]
}